[
    {
        "name": "Voidspawn",
        "championId": "TFT_VoidSpawn",
        "cost": 1,
        "traits": []
    },
    {
        "name": "Target Dummy",
        "championId": "TFT_TrainingDummy",
        "cost": 1,
        "traits": []
    },
    {
        "name": "Tome of Traits",
        "championId": "TFT5_EmblemArmoryKey",
        "cost": 7,
        "traits": []
    },
    {
        "name": "Vladimir",
        "championId": "TFT7_Vladimir",
        "cost": 1,
        "traits": [
            "Astral",
            "Mage"
        ]
    },
    {
        "name": "Nidalee",
        "championId": "TFT7_Nidalee",
        "cost": 1,
        "traits": [
            "Astral",
            "Shapeshifter"
        ]
    },
    {
        "name": "Senna",
        "championId": "TFT7_Senna",
        "cost": 1,
        "traits": [
            "Ragewing",
            "Cannoneer"
        ]
    },
    {
        "name": "Sett",
        "championId": "TFT7_Sett",
        "cost": 1,
        "traits": [
            "Ragewing",
            "Dragonmancer"
        ]
    },
    {
        "name": "Gnar",
        "championId": "TFT7_Gnar",
        "cost": 2,
        "traits": [
            "Jade",
            "Shapeshifter"
        ]
    },
    {
        "name": "Aatrox",
        "championId": "TFT7_Aatrox",
        "cost": 1,
        "traits": [
            "Shimmerscale",
            "Warrior"
        ]
    },
    {
        "name": "Diana",
        "championId": "TFT7_Diana",
        "cost": 3,
        "traits": [
            "Scalescorn",
            "Assassin"
        ]
    },
    {
        "name": "Sejuani",
        "championId": "TFT7_Sejuani",
        "cost": 1,
        "traits": [
            "Guild",
            "Cavalier"
        ]
    },
    {
        "name": "Ezreal",
        "championId": "TFT7_Ezreal",
        "cost": 1,
        "traits": [
            "Tempest",
            "Swiftshot"
        ]
    },
    {
        "name": "Nami",
        "championId": "TFT7_Nami",
        "cost": 2,
        "traits": [
            "Astral",
            "Mage",
            "Mystic"
        ]
    },
    {
        "name": "Skarner",
        "championId": "TFT7_Skarner",
        "cost": 1,
        "traits": [
            "Astral",
            "Bruiser"
        ]
    },
    {
        "name": "Swain",
        "championId": "TFT7_Swain",
        "cost": 3,
        "traits": [
            "Ragewing",
            "Dragonmancer",
            "Shapeshifter"
        ]
    },
    {
        "name": "Thresh",
        "championId": "TFT7_Thresh",
        "cost": 2,
        "traits": [
            "Whispers",
            "Guardian"
        ]
    },
    {
        "name": "Ashe",
        "championId": "TFT7_Ashe",
        "cost": 2,
        "traits": [
            "Jade",
            "Dragonmancer",
            "Swiftshot"
        ]
    },
    {
        "name": "Yone",
        "championId": "TFT7_Yone",
        "cost": 2,
        "traits": [
            "Mirage",
            "Warrior"
        ]
    },
    {
        "name": "Lillia",
        "championId": "TFT7_Lillia",
        "cost": 2,
        "traits": [
            "Scalescorn",
            "Cavalier",
            "Mage"
        ]
    },
    {
        "name": "Varus",
        "championId": "TFT7_Varus",
        "cost": 3,
        "traits": [
            "Astral",
            "Swiftshot"
        ]
    },
    {
        "name": "Lee Sin",
        "championId": "TFT7_LeeSin",
        "cost": 3,
        "traits": [
            "Tempest",
            "Dragonmancer"
        ]
    },
    {
        "name": "Shen",
        "championId": "TFT7_Shen",
        "cost": 2,
        "traits": [
            "Ragewing",
            "Bruiser",
            "Warrior"
        ]
    },
    {
        "name": "Elise",
        "championId": "TFT7_Elise",
        "cost": 3,
        "traits": [
            "Whispers",
            "Shapeshifter"
        ]
    },
    {
        "name": "Volibear",
        "championId": "TFT7_Volibear",
        "cost": 3,
        "traits": [
            "Shimmerscale",
            "Dragonmancer",
            "Legend"
        ]
    },
    {
        "name": "Olaf",
        "championId": "TFT7_Olaf",
        "cost": 3,
        "traits": [
            "Scalescorn",
            "Bruiser",
            "Warrior"
        ]
    },
    {
        "name": "Ryze",
        "championId": "TFT7_Ryze",
        "cost": 3,
        "traits": [
            "Guild",
            "Mage"
        ]
    },
    {
        "name": "Lulu",
        "championId": "TFT7_Lulu",
        "cost": 3,
        "traits": [
            "Trainer",
            "Mystic",
            "Evoker"
        ]
    },
    {
        "name": "Ornn",
        "championId": "TFT7_Ornn",
        "cost": 4,
        "traits": [
            "Tempest",
            "Bruiser",
            "Legend"
        ]
    },
    {
        "name": "Shyvana",
        "championId": "TFT7_Shyvana",
        "cost": 5,
        "traits": [
            "Ragewing",
            "Shapeshifter",
            "Dragon"
        ]
    },
    {
        "name": "Hecarim",
        "championId": "TFT7_Hecarim",
        "cost": 4,
        "traits": [
            "Ragewing",
            "Cavalier"
        ]
    },
    {
        "name": "Soraka",
        "championId": "TFT7_Soraka",
        "cost": 5,
        "traits": [
            "Jade",
            "Starcaller"
        ]
    },
    {
        "name": "Karma",
        "championId": "TFT7_Karma",
        "cost": 1,
        "traits": [
            "Jade",
            "Dragonmancer"
        ]
    },
    {
        "name": "Heimerdinger",
        "championId": "TFT7_Heimerdinger",
        "cost": 1,
        "traits": [
            "Trainer",
            "Mage"
        ]
    },
    {
        "name": "Tristana",
        "championId": "TFT7_Tristana",
        "cost": 2,
        "traits": [
            "Trainer",
            "Cannoneer"
        ]
    },
    {
        "name": "Anivia",
        "championId": "TFT7_Anivia",
        "cost": 3,
        "traits": [
            "Jade",
            "Evoker",
            "Legend"
        ]
    },
    {
        "name": "Talon",
        "championId": "TFT7_Talon",
        "cost": 4,
        "traits": [
            "Guild",
            "Assassin"
        ]
    },
    {
        "name": "Illaoi",
        "championId": "TFT7_Illaoi",
        "cost": 3,
        "traits": [
            "Astral",
            "Bruiser"
        ]
    },
    {
        "name": "Neeko",
        "championId": "TFT7_Neeko",
        "cost": 4,
        "traits": [
            "Jade",
            "Shapeshifter"
        ]
    },
    {
        "name": "Zoe",
        "championId": "TFT7_Zoe",
        "cost": 5,
        "traits": [
            "Shimmerscale",
            "Spell Thief",
            "Mage"
        ]
    },
    {
        "name": "Yasuo",
        "championId": "TFT7_Yasuo",
        "cost": 5,
        "traits": [
            "Mirage",
            "Dragonmancer",
            "Warrior"
        ]
    },
    {
        "name": "Corki",
        "championId": "TFT7_Corki",
        "cost": 4,
        "traits": [
            "Revel",
            "Cannoneer"
        ]
    },
    {
        "name": "Nunu & Willump",
        "championId": "TFT7_Nunu",
        "cost": 3,
        "traits": [
            "Mirage",
            "Cavalier"
        ]
    },
    {
        "name": "Bard",
        "championId": "TFT7_Bard",
        "cost": 5,
        "traits": [
            "Guild",
            "Mystic",
            "Bard"
        ]
    },
    {
        "name": "Zoe's Daisy",
        "championId": "TFT7_IvernMinion",
        "cost": 10,
        "traits": []
    },
    {
        "name": "Jinx",
        "championId": "TFT7_Jinx",
        "cost": 2,
        "traits": [
            "Revel",
            "Cannoneer"
        ]
    },
    {
        "name": "Kayn",
        "championId": "TFT7_Kayn",
        "cost": 2,
        "traits": [
            "Ragewing",
            "Shimmerscale",
            "Assassin"
        ]
    },
    {
        "name": "Xayah",
        "championId": "TFT7_Xayah",
        "cost": 4,
        "traits": [
            "Ragewing",
            "Swiftshot"
        ]
    },
    {
        "name": "Qiyana",
        "championId": "TFT7_Qiyana",
        "cost": 2,
        "traits": [
            "Tempest",
            "Assassin"
        ]
    },
    {
        "name": "Braum",
        "championId": "TFT7_Braum",
        "cost": 2,
        "traits": [
            "Scalescorn",
            "Guardian"
        ]
    },
    {
        "name": "Sylas",
        "championId": "TFT7_Sylas",
        "cost": 3,
        "traits": [
            "Whispers",
            "Mage",
            "Bruiser"
        ]
    },
    {
        "name": "Taric",
        "championId": "TFT7_Taric",
        "cost": 1,
        "traits": [
            "Jade",
            "Guardian"
        ]
    },
    {
        "name": "Leona",
        "championId": "TFT7_Leona",
        "cost": 1,
        "traits": [
            "Mirage",
            "Guardian"
        ]
    },
    {
        "name": "Twitch",
        "championId": "TFT7_Twitch",
        "cost": 2,
        "traits": [
            "Guild",
            "Swiftshot"
        ]
    },
    {
        "name": "The Golden Egg",
        "championId": "TFT6_TheGoldenEgg",
        "cost": 7,
        "traits": []
    },
    {
        "name": "Ao Shin",
        "championId": "TFT7_AoShin",
        "cost": 5,
        "traits": [
            "Tempest",
            "Dragon"
        ]
    },
    {
        "name": "Sy'fen",
        "championId": "TFT7_DragonPurple",
        "cost": 4,
        "traits": [
            "Whispers",
            "Bruiser",
            "Dragon"
        ]
    },
    {
        "name": "Shi Oh Yu",
        "championId": "TFT7_DragonGreen",
        "cost": 4,
        "traits": [
            "Jade",
            "Mystic",
            "Dragon"
        ]
    },
    {
        "name": "Idas",
        "championId": "TFT7_DragonGold",
        "cost": 4,
        "traits": [
            "Shimmerscale",
            "Dragon",
            "Guardian"
        ]
    },
    {
        "name": "Daeja",
        "championId": "TFT7_DragonBlue",
        "cost": 4,
        "traits": [
            "Mirage",
            "Dragon"
        ]
    },
    {
        "name": "Sona",
        "championId": "TFT7_Sona",
        "cost": 4,
        "traits": [
            "Revel",
            "Evoker"
        ]
    },
    {
        "name": "Nomsy",
        "championId": "TFT7_TrainerDragon",
        "cost": 10,
        "traits": []
    },
    {
        "name": "Jade Statue",
        "championId": "TFT7_JadeStatue",
        "cost": 10,
        "traits": []
    },
    {
        "name": "Pyke",
        "championId": "TFT7_Pyke",
        "cost": 5,
        "traits": [
            "Whispers",
            "Assassin"
        ]
    },
    {
        "name": "Tahm Kench",
        "championId": "TFT7_TahmKench",
        "cost": 1,
        "traits": [
            "Revel",
            "Bruiser"
        ]
    },
    {
        "name": "Aurelion Sol",
        "championId": "TFT7_AurelionSol",
        "cost": 5,
        "traits": [
            "Astral",
            "Evoker",
            "Dragon"
        ]
    }
]